[
{
  "name": "BlueTech Solutions SRL",
  "address": "Str. Libertatii Nr. 44, Timisoara, Romania",
  "phone": "+40 723 771 901",
  "email": "office@bluetechsolutions.ro",
  "website": "https://www.bluetechsolutions.ro"
},
{
"name": "Digital Pro Media SRL",
"address": "Bd. Independentei Nr. 120, Bucuresti, Romania",
"phone": "+40 746 512 003",
"email": "contact@digitalpromedia.ro",
"website": "https://www.digitalpromedia.ro"
},
{
"name": "AgroFarm Distribution SA",
"address": "Str. Carpatilor Nr. 18, Brasov, Romania",
"phone": "+40 752 115 839",
"email": "sales@agrofarm.ro",
"website": "https://www.agrofarm.ro"
},
{
"name": "NextGen Robotics SRL",
"address": "Str. Horea Nr. 12, Cluj-Napoca, Romania",
"phone": "+40 724 937 654",
"email": "info@nextgenrobotics.ro",
"website": "https://www.nextgenrobotics.ro"
},
{
"name": "Medilife Services SA",
"address": "Str. Clinicilor Nr. 20, Iasi, Romania",
"phone": "+40 744 328 740",
"email": "office@medilife.ro",
"website": "https://www.medilife.ro"
},
{
"name": "Urban Construct Group SRL",
"address": "Str. Traian Nr. 33, Constanta, Romania",
"phone": "+40 764 885 302",
"email": "contact@urbanconstructgroup.ro",
"website": "https://www.urbanconstructgroup.ro"
},
{
"name": "FreshFood Market SA",
"address": "Calea Bucuresti Nr. 91, Ploiesti, Romania",
"phone": "+40 751 800 442",
"email": "office@freshfoodmarket.ro",
"website": "https://www.freshfoodmarket.ro"
},
{
"name": "TechLine Software SRL",
"address": "Str. Unirii Nr. 13, Oradea, Romania",
"phone": "+40 723 660 900",
"email": "support@techlinesoftware.ro",
"website": "https://www.techlinesoftware.ro"
},
{
"name": "AutoParts Distribution SRL",
"address": "Str. Mihai Viteazul Nr. 67, Sibiu, Romania",
"phone": "+40 747 213 409",
"email": "sales@autopartsdistribution.ro",
"website": "https://www.autopartsdistribution.ro"
},
{
"name": "EcoEnergy Power SRL",
"address": "Str. Cloșca Nr. 21, Arad, Romania",
"phone": "+40 766 443 112",
"email": "office@ecoenergypower.ro",
"website": "https://www.ecoenergypower.ro"
},
{
"name": "SmartNet Systems SA",
"address": "Str. Carpați Nr. 10, Bucuresti, Romania",
"phone": "+40 755 101 980",
"email": "support@smartnetsystems.ro",
"website": "https://www.smartnetsystems.ro"
},
{
"name": "TopTravel Agency SRL",
"address": "Str. Republicii Nr. 33, Brasov, Romania",
"phone": "+40 767 498 223",
"email": "contact@toptravel.agency",
"website": "https://www.toptravel.agency"
},
{
"name": "Nova Engineering Group SA",
"address": "Bd. Eroilor Nr. 67, Cluj-Napoca, Romania",
"phone": "+40 745 556 002",
"email": "info@novaengineering.ro",
"website": "https://www.novaengineering.ro"
},
{
"name": "Sky Logistics Transport SRL",
"address": "Soseaua de Centura Nr. 8, Timisoara, Romania",
"phone": "+40 720 300 501",
"email": "dispatch@skylogisticstransport.ro",
"website": "https://www.skylogisticstransport.ro"
},
{
"name": "Helio Solar Tech SRL",
"address": "Str. Memorandumului Nr. 77, Cluj-Napoca, Romania",
"phone": "+40 754 882 934",
"email": "office@heliosolartech.ro",
"website": "https://www.heliosolartech.ro"
},
{
"name": "Elite Fitness Center SRL",
"address": "Str. Smardan Nr. 94, Bucuresti, Romania",
"phone": "+40 761 503 320",
"email": "info@elitefitness.ro",
"website": "https://www.elitefitness.ro"
},
{
"name": "Green Garden Landscaping SRL",
"address": "Str. Victoriei Nr. 150, Sibiu, Romania",
"phone": "+40 760 777 219",
"email": "contact@greengarden.ro",
"website": "https://www.greengarden.ro"
},
{
"name": "AquaPure Industry SA",
"address": "Bd. Tomis Nr. 255, Constanta, Romania",
"phone": "+40 744 335 882",
"email": "office@aquapureindustry.ro",
"website": "https://www.aquapureindustry.ro"
},
{
"name": "Royal Event Planning SRL",
"address": "Calea Victoriei Nr. 19, Bucuresti, Romania",
"phone": "+40 721 392 884",
"email": "info@royalevent.ro",
"website": "https://www.royalevent.ro"
},
{
"name": "SafeHome Security SRL",
"address": "Str. Carpatilor Nr. 100, Brasov, Romania",
"phone": "+40 724 882 030",
"email": "support@safehome.ro",
"website": "https://www.safehome.ro"
},
{
"name": "ProLegal Advisors SRL",
"address": "Str. Horea Nr. 50, Cluj-Napoca, Romania",
"phone": "+40 722 114 920",
"email": "office@prolegal.ro",
"website": "https://www.prolegal.ro"
},
{
"name": "HealthPlus Pharma SA",
"address": "Str. Clinicilor Nr. 81, Iasi, Romania",
"phone": "+40 760 204 887",
"email": "contact@healthpluspharma.ro",
"website": "https://www.healthpluspharma.ro"
},
{
"name": "BuildMaster Constructii SRL",
"address": "Str. Revolutiei Nr. 7, Arad, Romania",
"phone": "+40 765 900 144",
"email": "office@buildmaster.ro",
"website": "https://www.buildmaster.ro"
},
{
"name": "Nordic Wood Design SRL",
"address": "Str. Unirii Nr. 42, Oradea, Romania",
"phone": "+40 756 330 110",
"email": "design@nordicwood.ro",
"website": "https://www.nordicwood.ro"
},
{
"name": "ElectroMax Components SRL",
"address": "Str. Mihai Viteazul Nr. 5, Sibiu, Romania",
"phone": "+40 749 565 900",
"email": "support@electromax.ro",
"website": "https://www.electromax.ro"
},
{
"name": "Coffee Roasters Hub SRL",
"address": "Str. Libertatii Nr. 12, Timisoara, Romania",
"phone": "+40 721 449 333",
"email": "office@coffeeroastershub.ro",
"website": "https://www.coffeeroastershub.ro"
},
{
"name": "OceanWave Marine SA",
"address": "Bd. Tomis Nr. 310, Constanta, Romania",
"phone": "+40 760 727 231",
"email": "info@oceanwave.ro",
"website": "https://www.oceanwave.ro"
},
{
"name": "CityTaxi Mobility SRL",
"address": "Calea Bucuresti Nr. 190, Ploiesti, Romania",
"phone": "+40 751 710 627",
"email": "contact@citytaxi.ro",
"website": "https://www.citytaxi.ro"
},
{
"name": "Optima Digital Print SRL",
"address": "Str. Carpați Nr. 80, Bucuresti, Romania",
"phone": "+40 743 789 600",
"email": "info@optimadigital.ro",
"website": "https://www.optimadigital.ro"
},
{
"name": "UltraClean Services SRL",
"address": "Str. Smardan Nr. 87, Bucuresti, Romania",
"phone": "+40 722 730 522",
"email": "contact@ultraclean.ro",
"website": "https://www.ultraclean.ro"
},
{
"name": "TopSound Audio SRL",
"address": "Str. Republicii Nr. 77, Brasov, Romania",
"phone": "+40 744 111 002",
"email": "office@topsound.ro",
"website": "https://www.topsound.ro"
},
{
"name": "FutureEnergy Grid SA",
"address": "Str. Independentei Nr. 14, Cluj-Napoca, Romania",
"phone": "+40 761 558 908",
"email": "contact@futureenergy.ro",
"website": "https://www.futureenergy.ro"
},
{
"name": "Cosmos Data Intelligence SRL",
"address": "Str. Horea Nr. 91, Cluj-Napoca, Romania",
"phone": "+40 753 339 801",
"email": "office@cosmosdata.ro",
"website": "https://www.cosmosdata.ro"
},
{
"name": "SweetDelight Bakery SRL",
"address": "Str. Carpatilor Nr. 18, Brasov, Romania",
"phone": "+40 724 990 102",
"email": "office@sweetdelight.ro",
"website": "https://www.sweetdelight.ro"
},
{
"name": "RoyalSafe Insurance SA",
"address": "Bd. Victoriei Nr. 10, Bucuresti, Romania",
"phone": "+40 766 401 894",
"email": "info@royalsafe.ro",
"website": "https://www.royalsafe.ro"
},
{
"name": "Printorama Design SRL",
"address": "Str. Cloșca Nr. 25, Arad, Romania",
"phone": "+40 723 809 712",
"email": "contact@printorama.ro",
"website": "https://www.printorama.ro"
},
{
"name": "TransAuto Express SRL",
"address": "Soseaua de Centura Nr. 66, Timisoara, Romania",
"phone": "+40 762 992 211",
"email": "dispatch@transautoexpress.ro",
"website": "https://www.transautoexpress.ro"
},
{
"name": "GoldKey Real Estate SRL",
"address": "Calea Dorobanti Nr. 212, Bucuresti, Romania",
"phone": "+40 722 187 511",
"email": "office@goldkeyestate.ro",
"website": "https://www.goldkeyestate.ro"
},
{
"name": "Mountain Sports Gear SRL",
"address": "Str. Republicii Nr. 91, Brasov, Romania",
"phone": "+40 767 550 934",
"email": "info@mountainsports.ro",
"website": "https://www.mountainsports.ro"
},
{
"name": "Urban Mobility Bikes SRL",
"address": "Str. Carpați Nr. 12, Bucuresti, Romania",
"phone": "+40 747 881 220",
"email": "contact@urbmobility.ro",
"website": "https://www.urbmobility.ro"
},
{
"name": "SilverLine Consulting SRL",
"address": "Str. Libertatii Nr. 190, Timisoara, Romania",
"phone": "+40 771 440 102",
"email": "office@silverlineconsulting.ro",
"website": "https://www.silverlineconsulting.ro"
},
{
"name": "MegaFoods Distribution SA",
"address": "Bd. Tomis Nr. 399, Constanta, Romania",
"phone": "+40 750 229 911",
"email": "sales@megafoods.ro",
"website": "https://www.megafoods.ro"
},
{
"name": "Infinity Auto Service SRL",
"address": "Str. Mihai Viteazul Nr. 30, Sibiu, Romania",
"phone": "+40 756 452 870",
"email": "office@infinityauto.ro",
"website": "https://www.infinityauto.ro"
},
{
"name": "Neon Studio Creative SRL",
"address": "Str. Smardan Nr. 40, Bucuresti, Romania",
"phone": "+40 744 009 555",
"email": "contact@neonstudio.ro",
"website": "https://www.neonstudio.ro"
},
{
"name": "PureDrink Beverages SA",
"address": "Str. Carpatilor Nr. 77, Brasov, Romania",
"phone": "+40 761 339 221",
"email": "office@puredrink.ro",
"website": "https://www.puredrink.ro"
},
{
"name": "SpeedNet Telecom SRL",
"address": "Str. Independentei Nr. 92, Cluj-Napoca, Romania",
"phone": "+40 749 721 442",
"email": "support@speednetro.ro",
"website": "https://www.speednetro.ro"
},
{
"name": "NextLevel Training SRL",
"address": "Str. Horea Nr. 71, Cluj-Napoca, Romania",
"phone": "+40 722 599 044",
"email": "office@nextleveltraining.ro",
"website": "https://www.nextleveltraining.ro"
},
{
"name": "CoolAir HVAC Systems SRL",
"address": "Str. Cloșca Nr. 20, Arad, Romania",
"phone": "+40 756 778 441",
"email": "contact@coolair.ro",
"website": "https://www.coolair.ro"
},
{
"name": "WaterDrop Purifiers SA",
"address": "Calea Bucuresti Nr. 31, Ploiesti, Romania",
"phone": "+40 740 503 661",
"email": "office@waterdrop.ro",
"website": "https://www.waterdrop.ro"
},
{
"name": "BlueOcean Freight SRL",
"address": "Bd. Tomis Nr. 180, Constanta, Romania",
"phone": "+40 764 322 100",
"email": "dispatch@blueoceanfreight.ro",
"website": "https://www.blueoceanfreight.ro"
},
{
"name": "StarVision Optics SRL",
"address": "Str. Victor Babes Nr. 5, Iasi, Romania",
"phone": "+40 754 922 618",
"email": "contact@starvisionoptics.ro",
"website": "https://www.starvisionoptics.ro"
},
{
"name": "FoodMasters Catering SRL",
"address": "Str. Smardan Nr. 110, Bucuresti, Romania",
"phone": "+40 725 310 991",
"email": "office@foodmasters.ro",
"website": "https://www.foodmasters.ro"
}
]
